nqlog/__init__.py
nqlog/nqlog.py
nqlog-0.1.0.dist-info/LICENSE.md
nqlog-0.1.0.dist-info/METADATA
nqlog-0.1.0.dist-info/WHEEL
nqlog-0.1.0.dist-info/top_level.txt
nqlog-0.1.0.dist-info/RECORD
