Metadata-Version: 2.1
Name: nqlog
Version: 0.1.0
Summary: Interface to Google Cloud Logging that enables aggregated operation logs
Home-page: https://bitbucket.org/luca_de_alfaro/nqlog/src/master/
Author: Luca de Alfaro
Author-email: luca@dealfaro.com
Maintainer: Luca de Alfaro
Maintainer-email: luca@dealfaro.com
License: BSD
Platform: any
Classifier: Development Status :: 2 - Pre-Alpha
Classifier: Intended Audience :: Developers
Classifier: License :: OSI Approved :: BSD License
Classifier: Operating System :: OS Independent
Classifier: Programming Language :: Python
Classifier: Programming Language :: Python :: Implementation :: CPython
Classifier: Topic :: Software Development :: Libraries :: Python Modules
Requires-Python: >=3.7
Requires-Dist: datetime
Requires-Dist: logging
Requires-Dist: os
Requires-Dist: uuid
Requires-Dist: threading
Requires-Dist: traceback
Requires-Dist: google.cloud.logging
